maman/__init__.py
maman/__main__.py
maman/cli.py
maman-0.0.1.dist-info/METADATA
maman-0.0.1.dist-info/WHEEL
maman-0.0.1.dist-info/entry_points.txt
maman-0.0.1.dist-info/top_level.txt
maman-0.0.1.dist-info/RECORD
